eo4eu_base_utils/__init__.py
eo4eu_base_utils/optional.py
eo4eu_base_utils/utils.py
eo4eu_base_utils/result/__init__.py
eo4eu_base_utils/typing/__init__.py
eo4eu_base_utils/unify/__init__.py
eo4eu_base_utils-0.6.0.dist-info/METADATA
eo4eu_base_utils-0.6.0.dist-info/WHEEL
eo4eu_base_utils-0.6.0.dist-info/top_level.txt
eo4eu_base_utils-0.6.0.dist-info/RECORD
