Metadata-Version: 2.4
Name: eo4eu_base_utils
Version: 0.6.0
Summary: General utilities for EO4EU
Author-email: Apollon Grigoras <apollon@uoa.gr>
License-Expression: MIT
Classifier: Programming Language :: Python :: 3
Classifier: Programming Language :: Python :: 3.10
Classifier: Programming Language :: Python :: 3.11
Classifier: Programming Language :: Python :: 3.12
Classifier: Operating System :: OS Independent
Requires-Python: >=3.10
Requires-Dist: typing_extensions~=4.12; python_version <= "3.10"
Provides-Extra: docs
Requires-Dist: sphinx==8.2.3; extra == "docs"
Requires-Dist: sphinx-rtd-theme==3.0.2; extra == "docs"
